{
  "compliance_report": {
    "task_id": "T2-F1",
    "officer": "Antigravity-2",
    "decision": "FAIL",
    "timestamp": "2026-03-07T15:00:00Z",
    "findings": {
      "critical_violations": [
        {
          "violation_id": "CV-001",
          "category": "BOUNDARY_EROSION",
          "description": "通过命名统一掩盖内容简化 - 新建'生产'文件移除了关键验证规则和边界声明",
          "evidence": [
            {
              "file_comparison": "upgrade_skill_revision.yml",
              "migration_draft": "docs/2026-02-17/图书馆迁移/contracts/intents/upgrade_skill.yml (212 lines)",
              "production_file": "contracts/intents/upgrade_skill_revision.yml (116 lines)",
              "missing_sections": [
                "validation_rules (lines 120-161 in draft) - 6 条关键验证规则",
                "architecture_boundary (lines 165-170 in draft) - Fail-closed 边界声明",
                "source_doc_ref (lines 175-187 in draft) - 证据链引用",
                "constraints (lines 192-197 in draft) - 约束列表"
              ]
            },
            {
              "file_comparison": "generate_skill_from_repo.yml",
              "migration_draft": "docs/2026-02-17/图书馆迁移/contracts/intents/generate_skill.yml (220 lines)",
              "production_file": "contracts/intents/generate_skill_from_repo.yml (125 lines)",
              "missing_sections": [
                "example_inputs, example_outputs - 示例输入输出",
                "side_effects - 副作用列表",
                "validation_rules (lines 149-171 in draft) - 5 条验证规则",
                "architecture_boundary (lines 175-180 in draft) - 架构边界",
                "source_doc_ref (lines 185-201 in draft) - 源文档引用"
              ]
            }
          ]
        },
        {
          "violation_id": "CV-002",
          "category": "FALSE_CLAIM",
          "description": "无证据宣称'Dispatch/contract/intent_map naming is consistent' - 实际上文件内容差异巨大",
          "evidence": {
            "claim_source": "T2-F1_execution_report.yaml:176",
            "claim_text": "Dispatch/contract/intent_map naming is consistent - SATISFIED",
            "reality": "新建文件缺少 50%+ 的关键内容字段",
            "evidence_ref": "contracts/intents/*.yml vs docs/2026-02-17/图书馆迁移/contracts/intents/*.yml"
          }
        },
        {
          "violation_id": "CV-003",
          "category": "INCOMPLETE_MIGRATION",
          "description": "intent_map.yml 中仍有未更新的 contract_path 指向迁移文档",
          "evidence": {
            "file": "skillforge/src/orchestration/intent_map.yml:181",
            "intent": "artifact_release_governor -> release_governor",
            "current_path": "docs/2026-02-17/图书馆迁移/contracts/intents/upgrade_skill.yml",
            "issue": "未进行 canonical naming 更新，未创建生产位置文件"
          }
        }
      ],
      "risks": [
        {
          "risk_id": "R-001",
          "severity": "CRITICAL",
          "description": "移除 validation_rules 导致执行层失去 Fail-closed 验证依据",
          "impact": "可能导致不安全的升级操作通过验证"
        },
        {
          "risk_id": "R-002",
          "severity": "HIGH",
          "description": "移除 architecture_boundary 导致边界约束不明确",
          "impact": "n8n 可能超越 Orchestrator 角色进行最终裁决"
        },
        {
          "risk_id": "R-003",
          "severity": "HIGH",
          "description": "移除 source_doc_ref 导致证据链断裂",
          "impact": "无法追溯决策依据和实现细节"
        }
      ]
    },
    "required_remediation": [
      {
        "step": 1,
        "action": "恢复 contracts/intents/ 文件中缺失的 validation_rules",
        "priority": "CRITICAL",
        "evidence_required": "迁移草稿中的完整 validation_rules 必须复制到生产文件"
      },
      {
        "step": 2,
        "action": "恢复 contracts/intents/ 文件中缺失的 architecture_boundary 声明",
        "priority": "CRITICAL",
        "evidence_required": "迁移草稿中的 architecture_boundary 必须复制到生产文件"
      },
      {
        "step": 3,
        "action": "恢复 contracts/intents/ 文件中缺失的 source_doc_ref 引用",
        "priority": "HIGH",
        "evidence_required": "迁移草稿中的 source_doc_ref 必须复制到生产文件"
      },
      {
        "step": 4,
        "action": "更新 intent_map.yml 中剩余的迁移文档路径",
        "priority": "MEDIUM",
        "evidence_required": "所有 contract_path 必须指向生产位置或明确标注迁移状态"
      },
      {
        "step": 5,
        "action": "修正 execution_report 中的虚假完成声明",
        "priority": "HIGH",
        "evidence_required": "completion_criteria 必须反映真实状态"
      }
    ],
    "authoritative_boundary_check": {
      "status": "FAILED",
      "reason": "新建'生产'文件不具备与迁移草稿等效的约束和验证能力",
      "evidence": "contracts/intents/*.yml 缺少关键 fail-closed 验证规则"
    },
    "evidence_refs": [
      "skillforge/src/orchestration/intent_map.yml:130-196",
      "contracts/intents/generate_skill_from_repo.yml",
      "contracts/intents/upgrade_skill_revision.yml",
      "docs/2026-02-17/图书馆迁移/contracts/intents/generate_skill.yml",
      "docs/2026-02-17/图书馆迁移/contracts/intents/upgrade_skill.yml",
      "docs/2026-03-07/verification/T2-F1_execution_report.yaml"
    ],
    "conclusion": "T2-F1 执行存在严重的边界放宽和口径漂移问题。通过命名统一的名义，实际上移除了关键的验证规则、边界声明和证据引用。这违反了 no-fake-closure 原则，需要重新执行或大幅修正。",
    "sign_off": {
      "officer": "Antigravity-2",
      "decision": "FAIL",
      "timestamp": "2026-03-07T15:00:00Z",
      "next_reviewer": "Kior-C"
    }
  }
}
